MANIFEST.in
README.md
setup.cfg
setup.py
mmcv/__init__.py
mmcv/version.py
mmcv/arraymisc/__init__.py
mmcv/arraymisc/quantization.py
mmcv/cnn/__init__.py
mmcv/cnn/alexnet.py
mmcv/cnn/builder.py
mmcv/cnn/resnet.py
mmcv/cnn/vgg.py
mmcv/cnn/bricks/__init__.py
mmcv/cnn/bricks/activation.py
mmcv/cnn/bricks/context_block.py
mmcv/cnn/bricks/conv.py
mmcv/cnn/bricks/conv2d_adaptive_padding.py
mmcv/cnn/bricks/conv_module.py
mmcv/cnn/bricks/conv_ws.py
mmcv/cnn/bricks/depthwise_separable_conv_module.py
mmcv/cnn/bricks/generalized_attention.py
mmcv/cnn/bricks/hsigmoid.py
mmcv/cnn/bricks/hswish.py
mmcv/cnn/bricks/non_local.py
mmcv/cnn/bricks/norm.py
mmcv/cnn/bricks/padding.py
mmcv/cnn/bricks/plugin.py
mmcv/cnn/bricks/registry.py
mmcv/cnn/bricks/scale.py
mmcv/cnn/bricks/swish.py
mmcv/cnn/bricks/transformer.py
mmcv/cnn/bricks/upsample.py
mmcv/cnn/bricks/wrappers.py
mmcv/cnn/utils/__init__.py
mmcv/cnn/utils/flops_counter.py
mmcv/cnn/utils/fuse_conv_bn.py
mmcv/cnn/utils/weight_init.py
mmcv/engine/__init__.py
mmcv/engine/test.py
mmcv/fileio/__init__.py
mmcv/fileio/file_client.py
mmcv/fileio/io.py
mmcv/fileio/parse.py
mmcv/fileio/handlers/__init__.py
mmcv/fileio/handlers/base.py
mmcv/fileio/handlers/json_handler.py
mmcv/fileio/handlers/pickle_handler.py
mmcv/fileio/handlers/yaml_handler.py
mmcv/image/__init__.py
mmcv/image/colorspace.py
mmcv/image/geometric.py
mmcv/image/io.py
mmcv/image/misc.py
mmcv/image/photometric.py
mmcv/model_zoo/deprecated.json
mmcv/model_zoo/mmcls.json
mmcv/model_zoo/open_mmlab.json
mmcv/onnx/__init__.py
mmcv/onnx/info.py
mmcv/onnx/symbolic.py
mmcv/onnx/onnx_utils/__init__.py
mmcv/onnx/onnx_utils/symbolic_helper.py
mmcv/ops/__init__.py
mmcv/ops/bbox.py
mmcv/ops/box_iou_rotated.py
mmcv/ops/carafe.py
mmcv/ops/cc_attention.py
mmcv/ops/corner_pool.py
mmcv/ops/deform_conv.py
mmcv/ops/deform_roi_pool.py
mmcv/ops/deprecated_wrappers.py
mmcv/ops/focal_loss.py
mmcv/ops/fused_bias_leakyrelu.py
mmcv/ops/info.py
mmcv/ops/masked_conv.py
mmcv/ops/merge_cells.py
vitrox_mmcv_full.egg-info/PKG-INFO
vitrox_mmcv_full.egg-info/SOURCES.txt
vitrox_mmcv_full.egg-info/dependency_links.txt
vitrox_mmcv_full.egg-info/not-zip-safe
vitrox_mmcv_full.egg-info/requires.txt
vitrox_mmcv_full.egg-info/top_level.txt